{
"type": "FeatureCollection",
"crs": { "type": "name", "properties": { "name": "urn:ogc:def:crs:OGC:1.3:CRS84" } },
                                                                                
"features": [
{ "type": "Feature", "properties": { "eventname": "Utumno", "zoom": 4, "size": 2 }, "geometry": { "type": "Point", "coordinates": [ 0.022792780876819, -0.004415983527739 ] } }
]
}
